main.py
tasknow-1.0.8.dist-info/METADATA
tasknow-1.0.8.dist-info/WHEEL
tasknow-1.0.8.dist-info/entry_points.txt
tasknow-1.0.8.dist-info/top_level.txt
tasknow-1.0.8.dist-info/RECORD
