Metadata-Version: 2.4
Name: tasknow
Version: 1.0.8
Summary: A terminal to-do app that helps you focus on one task at a time.
Author: Decoding Chris
License-Expression: MIT
Project-URL: Homepage, https://github.com/decodingchris/TaskNow
Project-URL: Issues, https://github.com/decodingchris/TaskNow/issues
Classifier: Programming Language :: Python :: 3
Classifier: Programming Language :: Python :: 3.10
Classifier: Programming Language :: Python :: 3.11
Classifier: Programming Language :: Python :: 3.12
Classifier: Programming Language :: Python :: 3.13
Classifier: Operating System :: POSIX :: Linux
Classifier: Intended Audience :: End Users/Desktop
Classifier: Environment :: Console
Classifier: Topic :: Utilities
Requires-Python: >=3.10
